[
  {
    "firstName": "vikas",
    "LastName": "prince",
    "mobileNumber": "9666717618",
    "state": "andhra",
    "district": "",
    "pincode": "54464",
    "address": "Ramalayam street, Puttakonda Garuvu\r\nPedapudi mandal, East Godavari District.",
    "filter-check": "on"
  },
  {
    "firstName": "vikas",
    "LastName": "prince",
    "mobileNumber": "9666717618",
    "state": "andhra",
    "district": "",
    "pincode": "54464",
    "address": "Ramalayam street, Puttakonda Garuvu\r\nPedapudi mandal, East Godavari District.",
    "filter-check": "on"
  },
  {
    "firstName": "Vikas",
    "LastName": "Deyyala",
    "mobileNumber": "09666717618",
    "state": "andhra",
    "district": "",
    "pincode": "533344",
    "address": "Ramalayam street, Puttakonda Garuvu\r\nPedapudi mandal, East Godavari District.",
    "home": "on"
  },
  {
    "firstName": "Vikas",
    "LastName": "Deyyala",
    "mobileNumber": "09666717618",
    "state": "andhra",
    "district": "",
    "pincode": "533344",
    "address": "Ramalayam street, Puttakonda Garuvu\r\nPedapudi mandal, East Godavari District.",
    "home": "on"
  },
  {
    "firstName": "Vikas",
    "LastName": "Deyyala",
    "mobileNumber": "09666717618",
    "state": "andhra",
    "district": "",
    "pincode": "533344",
    "address": "Ramalayam street, Puttakonda Garuvu\r\nPedapudi mandal, East Godavari District.",
    "home": "on"
  },
  {
    "firstName": "Vikas",
    "LastName": "Deyyala",
    "mobileNumber": "09666717618",
    "state": "andhra",
    "district": "",
    "pincode": "533344",
    "address": "Ramalayam street, Puttakonda Garuvu\r\nPedapudi mandal, East Godavari District.",
    "home": "on"
  },
  {
    "firstName": "Vikas",
    "LastName": "Deyyala",
    "mobileNumber": "09666717618",
    "state": "andhra",
    "district": "",
    "pincode": "533344",
    "address": "Ramalayam street, Puttakonda Garuvu\r\nPedapudi mandal, East Godavari District.",
    "home": "on"
  },
  {
    "firstName": "Vikas",
    "LastName": "Deyyala",
    "mobileNumber": "09666717618",
    "state": "andhra",
    "district": "",
    "pincode": "533344",
    "address": "Ramalayam street, Puttakonda Garuvu\r\nPedapudi mandal, East Godavari District.",
    "Office": "on"
  },
  {
    "firstName": "Vikas",
    "LastName": "Deyyala",
    "mobileNumber": "09666717618",
    "state": "andhra",
    "district": "",
    "pincode": "533344",
    "address": "Ramalayam street, Puttakonda Garuvu\r\nPedapudi mandal, East Godavari District."
  },
  {
    "firstName": "Vikas",
    "LastName": "Deyyala",
    "mobileNumber": "09666717618",
    "state": "andhra",
    "district": "",
    "pincode": "533344",
    "address": "Ramalayam street, Puttakonda Garuvu\r\nPedapudi mandal, East Godavari District.",
    "home": "on"
  }
]
