[
  {
    "username": "vikas",
    "email": "vikas@gmail.com",
    "password": "$2b$10$dDuyY0fqPeA.WKl5Bokgl.B3ay96r0AJFkYK3SKPEXk4Y4U/t/RmK"
  },
  {
    "username": "vikas",
    "email": "vikaslovely00@gmail.com",
    "password": "$2b$10$nC4ZGncLDvhyC3.3wxPYr.fcJJQ3axpeXJz98IW1tDqDoce5u2RAu"
  },
  {
    "username": "vardhan",
    "email": "vardhan@gmail.com",
    "password": "$2b$10$FWq7Lfss7hqVYwmWs1ACrOi8/Cggb8FY0GrAZp0ztXiznehUIHPmy"
  },
  {
    "username": "pinky",
    "email": "pinky@gmail.com",
    "password": "$2b$10$hfDk.Z1k83HnM0E90ouSGOmUjaRG7kCoQCqFcT4seHv6Gs5CvJoiS"
  },
  {
    "username": "ajay",
    "email": "ajay@lpu.in",
    "password": "$2b$10$FL6uokGd85cL9B.c1lYtMejYjWlbhG659UW2NFv6ADSCr3/ulCDte"
  },
  {
    "username": "ajayreddy",
    "email": "ajay@google.com",
    "password": "$2b$10$lKnSBDZ492rPQlX6uGkBWOscnX/dAuTIUTOF22F9a2dKWsuFwaaay"
  },
  {
    "username": "donkey",
    "email": "donkey@gmail.com",
    "password": "$2b$10$oTKVpdUXnHhKnjQO1ofM1OaT7k2TQ7NDgXVYXlT9WtF0iEy1DvTqW"
  },
  {
    "username": "rahul",
    "email": "rahul@gmail.com",
    "password": "$2b$10$gqMtzD7qFb/iAOkvtIpAHOeUinevmzAx3PnwLCzUfnel.6wFau5xm"
  },
  {
    "username": "Rayudu",
    "email": "rayudu@gmail.com",
    "password": "$2b$10$1Mv2o7Gfz5FWmRdQHOvulOc/8eLKN8Mpg9IwdEvqQH5pUkjDK5kJe"
  },
  {
    "username": "dhanush",
    "email": "dhanush@gmail.com",
    "password": "$2b$10$91q6I5LadwInIjXLQNmauu9pqlzQzb1g.rs86Q.60BoGs6L9jvx9."
  }
]
